{"nodes": [{"id": "f_anti_zensynora_myclaw_tools_toolbox_py", "label": "toolbox.py", "file_type": "code", "source_file": "F:\\ANTI\\zensynora\\myclaw\\tools\\toolbox.py", "source_location": "L1"}, {"id": "toolbox_list_tools", "label": "list_tools()", "file_type": "code", "source_file": "F:\\ANTI\\zensynora\\myclaw\\tools\\toolbox.py", "source_location": "L46"}, {"id": "toolbox_register_mcp_tool", "label": "register_mcp_tool()", "file_type": "code", "source_file": "F:\\ANTI\\zensynora\\myclaw\\tools\\toolbox.py", "source_location": "L51"}, {"id": "toolbox_register_tool", "label": "register_tool()", "file_type": "code", "source_file": "F:\\ANTI\\zensynora\\myclaw\\tools\\toolbox.py", "source_location": "L59"}, {"id": "toolbox_update_toolbox_readme", "label": "_update_toolbox_readme()", "file_type": "code", "source_file": "F:\\ANTI\\zensynora\\myclaw\\tools\\toolbox.py", "source_location": "L297"}, {"id": "toolbox_list_toolbox", "label": "list_toolbox()", "file_type": "code", "source_file": "F:\\ANTI\\zensynora\\myclaw\\tools\\toolbox.py", "source_location": "L337"}, {"id": "toolbox_get_tool_documentation", "label": "get_tool_documentation()", "file_type": "code", "source_file": "F:\\ANTI\\zensynora\\myclaw\\tools\\toolbox.py", "source_location": "L379"}, {"id": "toolbox_load_custom_tools", "label": "load_custom_tools()", "file_type": "code", "source_file": "F:\\ANTI\\zensynora\\myclaw\\tools\\toolbox.py", "source_location": "L405"}, {"id": "toolbox_get_skill_info", "label": "get_skill_info()", "file_type": "code", "source_file": "F:\\ANTI\\zensynora\\myclaw\\tools\\toolbox.py", "source_location": "L453"}, {"id": "toolbox_enable_skill", "label": "enable_skill()", "file_type": "code", "source_file": "F:\\ANTI\\zensynora\\myclaw\\tools\\toolbox.py", "source_location": "L505"}, {"id": "toolbox_disable_skill", "label": "disable_skill()", "file_type": "code", "source_file": "F:\\ANTI\\zensynora\\myclaw\\tools\\toolbox.py", "source_location": "L554"}, {"id": "toolbox_update_skill_metadata", "label": "update_skill_metadata()", "file_type": "code", "source_file": "F:\\ANTI\\zensynora\\myclaw\\tools\\toolbox.py", "source_location": "L588"}, {"id": "toolbox_benchmark_skill", "label": "benchmark_skill()", "file_type": "code", "source_file": "F:\\ANTI\\zensynora\\myclaw\\tools\\toolbox.py", "source_location": "L640"}, {"id": "toolbox_evaluate_skill", "label": "evaluate_skill()", "file_type": "code", "source_file": "F:\\ANTI\\zensynora\\myclaw\\tools\\toolbox.py", "source_location": "L754"}, {"id": "toolbox_improve_skill", "label": "improve_skill()", "file_type": "code", "source_file": "F:\\ANTI\\zensynora\\myclaw\\tools\\toolbox.py", "source_location": "L872"}, {"id": "toolbox_rollback_skill", "label": "rollback_skill()", "file_type": "code", "source_file": "F:\\ANTI\\zensynora\\myclaw\\tools\\toolbox.py", "source_location": "L1064"}, {"id": "toolbox_rationale_1", "label": "Tools \u2014 TOOLBOX Skill Management", "file_type": "rationale", "source_file": "F:\\ANTI\\zensynora\\myclaw\\tools\\toolbox.py", "source_location": "L1"}, {"id": "toolbox_rationale_47", "label": "Return the names of all currently registered tools.", "file_type": "rationale", "source_file": "F:\\ANTI\\zensynora\\myclaw\\tools\\toolbox.py", "source_location": "L47"}, {"id": "toolbox_rationale_52", "label": "Register a remote tool retrieved via MCP.", "file_type": "rationale", "source_file": "F:\\ANTI\\zensynora\\myclaw\\tools\\toolbox.py", "source_location": "L52"}, {"id": "toolbox_rationale_60", "label": "Dynamically create a new tool from Python source code and store it in TOOLBOX.", "file_type": "rationale", "source_file": "F:\\ANTI\\zensynora\\myclaw\\tools\\toolbox.py", "source_location": "L60"}, {"id": "toolbox_rationale_298", "label": "Update the main TOOLBOX README with a list of all tools.", "file_type": "rationale", "source_file": "F:\\ANTI\\zensynora\\myclaw\\tools\\toolbox.py", "source_location": "L298"}, {"id": "toolbox_rationale_338", "label": "List all custom tools stored in the TOOLBOX with metadata.      Reads the TOOL", "file_type": "rationale", "source_file": "F:\\ANTI\\zensynora\\myclaw\\tools\\toolbox.py", "source_location": "L338"}, {"id": "toolbox_rationale_380", "label": "Get the full documentation for a specific TOOLBOX tool by name.      Reads and", "file_type": "rationale", "source_file": "F:\\ANTI\\zensynora\\myclaw\\tools\\toolbox.py", "source_location": "L380"}, {"id": "toolbox_rationale_406", "label": "Load persisted custom tools from TOOLBOX at startup \u2014 called by gateway.py / cli", "file_type": "rationale", "source_file": "F:\\ANTI\\zensynora\\myclaw\\tools\\toolbox.py", "source_location": "L406"}, {"id": "toolbox_rationale_454", "label": "Get detailed information about a skill from the TOOLBOX registry.      skill_n", "file_type": "rationale", "source_file": "F:\\ANTI\\zensynora\\myclaw\\tools\\toolbox.py", "source_location": "L454"}, {"id": "toolbox_rationale_506", "label": "Enable a disabled skill in the TOOLBOX.      skill_name: The name of the skill", "file_type": "rationale", "source_file": "F:\\ANTI\\zensynora\\myclaw\\tools\\toolbox.py", "source_location": "L506"}, {"id": "toolbox_rationale_555", "label": "Disable an enabled skill in the TOOLBOX (soft delete).      skill_name: The na", "file_type": "rationale", "source_file": "F:\\ANTI\\zensynora\\myclaw\\tools\\toolbox.py", "source_location": "L555"}, {"id": "toolbox_rationale_591", "label": "Update metadata for an existing skill.      skill_name: The name of the skill", "file_type": "rationale", "source_file": "F:\\ANTI\\zensynora\\myclaw\\tools\\toolbox.py", "source_location": "L591"}, {"id": "toolbox_rationale_641", "label": "Run benchmark tests against a skill and return evaluation results.      skill_", "file_type": "rationale", "source_file": "F:\\ANTI\\zensynora\\myclaw\\tools\\toolbox.py", "source_location": "L641"}, {"id": "toolbox_rationale_755", "label": "Run basic evaluation tests on a skill.      Performs a simple sanity check:", "file_type": "rationale", "source_file": "F:\\ANTI\\zensynora\\myclaw\\tools\\toolbox.py", "source_location": "L755"}, {"id": "toolbox_rationale_873", "label": "Improve an existing skill with new code, with safety checks and evaluation.", "file_type": "rationale", "source_file": "F:\\ANTI\\zensynora\\myclaw\\tools\\toolbox.py", "source_location": "L873"}, {"id": "toolbox_rationale_1065", "label": "Rollback a skill to its previous version if a backup exists.      skill_name:", "file_type": "rationale", "source_file": "F:\\ANTI\\zensynora\\myclaw\\tools\\toolbox.py", "source_location": "L1065"}], "edges": [{"source": "f_anti_zensynora_myclaw_tools_toolbox_py", "target": "asyncio", "relation": "imports", "confidence": "EXTRACTED", "source_file": "F:\\ANTI\\zensynora\\myclaw\\tools\\toolbox.py", "source_location": "L5", "weight": 1.0}, {"source": "f_anti_zensynora_myclaw_tools_toolbox_py", "target": "f_anti_zensynora_myclaw_tools_async_utils_py", "relation": "imports_from", "confidence": "EXTRACTED", "source_file": "F:\\ANTI\\zensynora\\myclaw\\tools\\toolbox.py", "source_location": "L6", "weight": 1.0}, {"source": "f_anti_zensynora_myclaw_tools_toolbox_py", "target": "logging", "relation": "imports", "confidence": "EXTRACTED", "source_file": "F:\\ANTI\\zensynora\\myclaw\\tools\\toolbox.py", "source_location": "L7", "weight": 1.0}, {"source": "f_anti_zensynora_myclaw_tools_toolbox_py", "target": "typing", "relation": "imports_from", "confidence": "EXTRACTED", "source_file": "F:\\ANTI\\zensynora\\myclaw\\tools\\toolbox.py", "source_location": "L8", "weight": 1.0}, {"source": "f_anti_zensynora_myclaw_tools_toolbox_py", "target": "f_anti_zensynora_myclaw_tools_core_py", "relation": "imports_from", "confidence": "EXTRACTED", "source_file": "F:\\ANTI\\zensynora\\myclaw\\tools\\toolbox.py", "source_location": "L10", "weight": 1.0}, {"source": "f_anti_zensynora_myclaw_tools_toolbox_py", "target": "importlib_util", "relation": "imports", "confidence": "EXTRACTED", "source_file": "F:\\ANTI\\zensynora\\myclaw\\tools\\toolbox.py", "source_location": "L32", "weight": 1.0}, {"source": "f_anti_zensynora_myclaw_tools_toolbox_py", "target": "json", "relation": "imports", "confidence": "EXTRACTED", "source_file": "F:\\ANTI\\zensynora\\myclaw\\tools\\toolbox.py", "source_location": "L33", "weight": 1.0}, {"source": "f_anti_zensynora_myclaw_tools_toolbox_py", "target": "time", "relation": "imports", "confidence": "EXTRACTED", "source_file": "F:\\ANTI\\zensynora\\myclaw\\tools\\toolbox.py", "source_location": "L34", "weight": 1.0}, {"source": "f_anti_zensynora_myclaw_tools_toolbox_py", "target": "re", "relation": "imports", "confidence": "EXTRACTED", "source_file": "F:\\ANTI\\zensynora\\myclaw\\tools\\toolbox.py", "source_location": "L35", "weight": 1.0}, {"source": "f_anti_zensynora_myclaw_tools_toolbox_py", "target": "asyncio", "relation": "imports", "confidence": "EXTRACTED", "source_file": "F:\\ANTI\\zensynora\\myclaw\\tools\\toolbox.py", "source_location": "L36", "weight": 1.0}, {"source": "f_anti_zensynora_myclaw_tools_toolbox_py", "target": "inspect", "relation": "imports", "confidence": "EXTRACTED", "source_file": "F:\\ANTI\\zensynora\\myclaw\\tools\\toolbox.py", "source_location": "L37", "weight": 1.0}, {"source": "f_anti_zensynora_myclaw_tools_toolbox_py", "target": "pathlib", "relation": "imports_from", "confidence": "EXTRACTED", "source_file": "F:\\ANTI\\zensynora\\myclaw\\tools\\toolbox.py", "source_location": "L38", "weight": 1.0}, {"source": "f_anti_zensynora_myclaw_tools_toolbox_py", "target": "datetime", "relation": "imports_from", "confidence": "EXTRACTED", "source_file": "F:\\ANTI\\zensynora\\myclaw\\tools\\toolbox.py", "source_location": "L39", "weight": 1.0}, {"source": "f_anti_zensynora_myclaw_tools_toolbox_py", "target": "toolbox_list_tools", "relation": "contains", "confidence": "EXTRACTED", "source_file": "F:\\ANTI\\zensynora\\myclaw\\tools\\toolbox.py", "source_location": "L46", "weight": 1.0}, {"source": "f_anti_zensynora_myclaw_tools_toolbox_py", "target": "toolbox_register_mcp_tool", "relation": "contains", "confidence": "EXTRACTED", "source_file": "F:\\ANTI\\zensynora\\myclaw\\tools\\toolbox.py", "source_location": "L51", "weight": 1.0}, {"source": "f_anti_zensynora_myclaw_tools_toolbox_py", "target": "toolbox_register_tool", "relation": "contains", "confidence": "EXTRACTED", "source_file": "F:\\ANTI\\zensynora\\myclaw\\tools\\toolbox.py", "source_location": "L59", "weight": 1.0}, {"source": "f_anti_zensynora_myclaw_tools_toolbox_py", "target": "toolbox_update_toolbox_readme", "relation": "contains", "confidence": "EXTRACTED", "source_file": "F:\\ANTI\\zensynora\\myclaw\\tools\\toolbox.py", "source_location": "L297", "weight": 1.0}, {"source": "f_anti_zensynora_myclaw_tools_toolbox_py", "target": "toolbox_list_toolbox", "relation": "contains", "confidence": "EXTRACTED", "source_file": "F:\\ANTI\\zensynora\\myclaw\\tools\\toolbox.py", "source_location": "L337", "weight": 1.0}, {"source": "f_anti_zensynora_myclaw_tools_toolbox_py", "target": "toolbox_get_tool_documentation", "relation": "contains", "confidence": "EXTRACTED", "source_file": "F:\\ANTI\\zensynora\\myclaw\\tools\\toolbox.py", "source_location": "L379", "weight": 1.0}, {"source": "f_anti_zensynora_myclaw_tools_toolbox_py", "target": "toolbox_load_custom_tools", "relation": "contains", "confidence": "EXTRACTED", "source_file": "F:\\ANTI\\zensynora\\myclaw\\tools\\toolbox.py", "source_location": "L405", "weight": 1.0}, {"source": "f_anti_zensynora_myclaw_tools_toolbox_py", "target": "toolbox_get_skill_info", "relation": "contains", "confidence": "EXTRACTED", "source_file": "F:\\ANTI\\zensynora\\myclaw\\tools\\toolbox.py", "source_location": "L453", "weight": 1.0}, {"source": "f_anti_zensynora_myclaw_tools_toolbox_py", "target": "toolbox_enable_skill", "relation": "contains", "confidence": "EXTRACTED", "source_file": "F:\\ANTI\\zensynora\\myclaw\\tools\\toolbox.py", "source_location": "L505", "weight": 1.0}, {"source": "f_anti_zensynora_myclaw_tools_toolbox_py", "target": "toolbox_disable_skill", "relation": "contains", "confidence": "EXTRACTED", "source_file": "F:\\ANTI\\zensynora\\myclaw\\tools\\toolbox.py", "source_location": "L554", "weight": 1.0}, {"source": "f_anti_zensynora_myclaw_tools_toolbox_py", "target": "toolbox_update_skill_metadata", "relation": "contains", "confidence": "EXTRACTED", "source_file": "F:\\ANTI\\zensynora\\myclaw\\tools\\toolbox.py", "source_location": "L588", "weight": 1.0}, {"source": "f_anti_zensynora_myclaw_tools_toolbox_py", "target": "toolbox_benchmark_skill", "relation": "contains", "confidence": "EXTRACTED", "source_file": "F:\\ANTI\\zensynora\\myclaw\\tools\\toolbox.py", "source_location": "L640", "weight": 1.0}, {"source": "f_anti_zensynora_myclaw_tools_toolbox_py", "target": "toolbox_evaluate_skill", "relation": "contains", "confidence": "EXTRACTED", "source_file": "F:\\ANTI\\zensynora\\myclaw\\tools\\toolbox.py", "source_location": "L754", "weight": 1.0}, {"source": "f_anti_zensynora_myclaw_tools_toolbox_py", "target": "toolbox_improve_skill", "relation": "contains", "confidence": "EXTRACTED", "source_file": "F:\\ANTI\\zensynora\\myclaw\\tools\\toolbox.py", "source_location": "L872", "weight": 1.0}, {"source": "f_anti_zensynora_myclaw_tools_toolbox_py", "target": "toolbox_rollback_skill", "relation": "contains", "confidence": "EXTRACTED", "source_file": "F:\\ANTI\\zensynora\\myclaw\\tools\\toolbox.py", "source_location": "L1064", "weight": 1.0}, {"source": "toolbox_register_tool", "target": "toolbox_update_toolbox_readme", "relation": "calls", "confidence": "EXTRACTED", "source_file": "F:\\ANTI\\zensynora\\myclaw\\tools\\toolbox.py", "source_location": "L248", "weight": 1.0}, {"source": "toolbox_load_custom_tools", "target": "toolbox_update_toolbox_readme", "relation": "calls", "confidence": "EXTRACTED", "source_file": "F:\\ANTI\\zensynora\\myclaw\\tools\\toolbox.py", "source_location": "L441", "weight": 1.0}, {"source": "toolbox_rationale_1", "target": "f_anti_zensynora_myclaw_tools_toolbox_py", "relation": "rationale_for", "confidence": "EXTRACTED", "source_file": "F:\\ANTI\\zensynora\\myclaw\\tools\\toolbox.py", "source_location": "L1", "weight": 1.0}, {"source": "toolbox_rationale_47", "target": "toolbox_list_tools", "relation": "rationale_for", "confidence": "EXTRACTED", "source_file": "F:\\ANTI\\zensynora\\myclaw\\tools\\toolbox.py", "source_location": "L47", "weight": 1.0}, {"source": "toolbox_rationale_52", "target": "toolbox_register_mcp_tool", "relation": "rationale_for", "confidence": "EXTRACTED", "source_file": "F:\\ANTI\\zensynora\\myclaw\\tools\\toolbox.py", "source_location": "L52", "weight": 1.0}, {"source": "toolbox_rationale_60", "target": "toolbox_register_tool", "relation": "rationale_for", "confidence": "EXTRACTED", "source_file": "F:\\ANTI\\zensynora\\myclaw\\tools\\toolbox.py", "source_location": "L60", "weight": 1.0}, {"source": "toolbox_rationale_298", "target": "toolbox_update_toolbox_readme", "relation": "rationale_for", "confidence": "EXTRACTED", "source_file": "F:\\ANTI\\zensynora\\myclaw\\tools\\toolbox.py", "source_location": "L298", "weight": 1.0}, {"source": "toolbox_rationale_338", "target": "toolbox_list_toolbox", "relation": "rationale_for", "confidence": "EXTRACTED", "source_file": "F:\\ANTI\\zensynora\\myclaw\\tools\\toolbox.py", "source_location": "L338", "weight": 1.0}, {"source": "toolbox_rationale_380", "target": "toolbox_get_tool_documentation", "relation": "rationale_for", "confidence": "EXTRACTED", "source_file": "F:\\ANTI\\zensynora\\myclaw\\tools\\toolbox.py", "source_location": "L380", "weight": 1.0}, {"source": "toolbox_rationale_406", "target": "toolbox_load_custom_tools", "relation": "rationale_for", "confidence": "EXTRACTED", "source_file": "F:\\ANTI\\zensynora\\myclaw\\tools\\toolbox.py", "source_location": "L406", "weight": 1.0}, {"source": "toolbox_rationale_454", "target": "toolbox_get_skill_info", "relation": "rationale_for", "confidence": "EXTRACTED", "source_file": "F:\\ANTI\\zensynora\\myclaw\\tools\\toolbox.py", "source_location": "L454", "weight": 1.0}, {"source": "toolbox_rationale_506", "target": "toolbox_enable_skill", "relation": "rationale_for", "confidence": "EXTRACTED", "source_file": "F:\\ANTI\\zensynora\\myclaw\\tools\\toolbox.py", "source_location": "L506", "weight": 1.0}, {"source": "toolbox_rationale_555", "target": "toolbox_disable_skill", "relation": "rationale_for", "confidence": "EXTRACTED", "source_file": "F:\\ANTI\\zensynora\\myclaw\\tools\\toolbox.py", "source_location": "L555", "weight": 1.0}, {"source": "toolbox_rationale_591", "target": "toolbox_update_skill_metadata", "relation": "rationale_for", "confidence": "EXTRACTED", "source_file": "F:\\ANTI\\zensynora\\myclaw\\tools\\toolbox.py", "source_location": "L591", "weight": 1.0}, {"source": "toolbox_rationale_641", "target": "toolbox_benchmark_skill", "relation": "rationale_for", "confidence": "EXTRACTED", "source_file": "F:\\ANTI\\zensynora\\myclaw\\tools\\toolbox.py", "source_location": "L641", "weight": 1.0}, {"source": "toolbox_rationale_755", "target": "toolbox_evaluate_skill", "relation": "rationale_for", "confidence": "EXTRACTED", "source_file": "F:\\ANTI\\zensynora\\myclaw\\tools\\toolbox.py", "source_location": "L755", "weight": 1.0}, {"source": "toolbox_rationale_873", "target": "toolbox_improve_skill", "relation": "rationale_for", "confidence": "EXTRACTED", "source_file": "F:\\ANTI\\zensynora\\myclaw\\tools\\toolbox.py", "source_location": "L873", "weight": 1.0}, {"source": "toolbox_rationale_1065", "target": "toolbox_rollback_skill", "relation": "rationale_for", "confidence": "EXTRACTED", "source_file": "F:\\ANTI\\zensynora\\myclaw\\tools\\toolbox.py", "source_location": "L1065", "weight": 1.0}], "raw_calls": [{"caller_nid": "toolbox_list_tools", "callee": "join", "source_file": "F:\\ANTI\\zensynora\\myclaw\\tools\\toolbox.py", "source_location": "L48"}, {"caller_nid": "toolbox_list_tools", "callee": "sorted", "source_file": "F:\\ANTI\\zensynora\\myclaw\\tools\\toolbox.py", "source_location": "L48"}, {"caller_nid": "toolbox_list_tools", "callee": "keys", "source_file": "F:\\ANTI\\zensynora\\myclaw\\tools\\toolbox.py", "source_location": "L48"}, {"caller_nid": "toolbox_register_tool", "callee": "isidentifier", "source_file": "F:\\ANTI\\zensynora\\myclaw\\tools\\toolbox.py", "source_location": "L77"}, {"caller_nid": "toolbox_register_tool", "callee": "mkdir", "source_file": "F:\\ANTI\\zensynora\\myclaw\\tools\\toolbox.py", "source_location": "L116"}, {"caller_nid": "toolbox_register_tool", "callee": "exists", "source_file": "F:\\ANTI\\zensynora\\myclaw\\tools\\toolbox.py", "source_location": "L118"}, {"caller_nid": "toolbox_register_tool", "callee": "keys", "source_file": "F:\\ANTI\\zensynora\\myclaw\\tools\\toolbox.py", "source_location": "L123"}, {"caller_nid": "toolbox_register_tool", "callee": "lower", "source_file": "F:\\ANTI\\zensynora\\myclaw\\tools\\toolbox.py", "source_location": "L123"}, {"caller_nid": "toolbox_register_tool", "callee": "lower", "source_file": "F:\\ANTI\\zensynora\\myclaw\\tools\\toolbox.py", "source_location": "L123"}, {"caller_nid": "toolbox_register_tool", "callee": "lower", "source_file": "F:\\ANTI\\zensynora\\myclaw\\tools\\toolbox.py", "source_location": "L123"}, {"caller_nid": "toolbox_register_tool", "callee": "lower", "source_file": "F:\\ANTI\\zensynora\\myclaw\\tools\\toolbox.py", "source_location": "L123"}, {"caller_nid": "toolbox_register_tool", "callee": "join", "source_file": "F:\\ANTI\\zensynora\\myclaw\\tools\\toolbox.py", "source_location": "L126"}, {"caller_nid": "toolbox_register_tool", "callee": "compile", "source_file": "F:\\ANTI\\zensynora\\myclaw\\tools\\toolbox.py", "source_location": "L130"}, {"caller_nid": "toolbox_register_tool", "callee": "parse", "source_file": "F:\\ANTI\\zensynora\\myclaw\\tools\\toolbox.py", "source_location": "L138"}, {"caller_nid": "toolbox_register_tool", "callee": "walk", "source_file": "F:\\ANTI\\zensynora\\myclaw\\tools\\toolbox.py", "source_location": "L186"}, {"caller_nid": "toolbox_register_tool", "callee": "isinstance", "source_file": "F:\\ANTI\\zensynora\\myclaw\\tools\\toolbox.py", "source_location": "L187"}, {"caller_nid": "toolbox_register_tool", "callee": "split", "source_file": "F:\\ANTI\\zensynora\\myclaw\\tools\\toolbox.py", "source_location": "L189"}, {"caller_nid": "toolbox_register_tool", "callee": "isinstance", "source_file": "F:\\ANTI\\zensynora\\myclaw\\tools\\toolbox.py", "source_location": "L191"}, {"caller_nid": "toolbox_register_tool", "callee": "split", "source_file": "F:\\ANTI\\zensynora\\myclaw\\tools\\toolbox.py", "source_location": "L192"}, {"caller_nid": "toolbox_register_tool", "callee": "isinstance", "source_file": "F:\\ANTI\\zensynora\\myclaw\\tools\\toolbox.py", "source_location": "L196"}, {"caller_nid": "toolbox_register_tool", "callee": "isinstance", "source_file": "F:\\ANTI\\zensynora\\myclaw\\tools\\toolbox.py", "source_location": "L198"}, {"caller_nid": "toolbox_register_tool", "callee": "isinstance", "source_file": "F:\\ANTI\\zensynora\\myclaw\\tools\\toolbox.py", "source_location": "L202"}, {"caller_nid": "toolbox_register_tool", "callee": "_is_builtin_access", "source_file": "F:\\ANTI\\zensynora\\myclaw\\tools\\toolbox.py", "source_location": "L205"}, {"caller_nid": "toolbox_register_tool", "callee": "isinstance", "source_file": "F:\\ANTI\\zensynora\\myclaw\\tools\\toolbox.py", "source_location": "L207"}, {"caller_nid": "toolbox_register_tool", "callee": "_is_builtin_access", "source_file": "F:\\ANTI\\zensynora\\myclaw\\tools\\toolbox.py", "source_location": "L208"}, {"caller_nid": "toolbox_register_tool", "callee": "write_text", "source_file": "F:\\ANTI\\zensynora\\myclaw\\tools\\toolbox.py", "source_location": "L224"}, {"caller_nid": "toolbox_register_tool", "callee": "isoformat", "source_file": "F:\\ANTI\\zensynora\\myclaw\\tools\\toolbox.py", "source_location": "L240"}, {"caller_nid": "toolbox_register_tool", "callee": "now", "source_file": "F:\\ANTI\\zensynora\\myclaw\\tools\\toolbox.py", "source_location": "L240"}, {"caller_nid": "toolbox_register_tool", "callee": "write_text", "source_file": "F:\\ANTI\\zensynora\\myclaw\\tools\\toolbox.py", "source_location": "L245"}, {"caller_nid": "toolbox_register_tool", "callee": "spec_from_file_location", "source_file": "F:\\ANTI\\zensynora\\myclaw\\tools\\toolbox.py", "source_location": "L252"}, {"caller_nid": "toolbox_register_tool", "callee": "module_from_spec", "source_file": "F:\\ANTI\\zensynora\\myclaw\\tools\\toolbox.py", "source_location": "L253"}, {"caller_nid": "toolbox_register_tool", "callee": "exec_module", "source_file": "F:\\ANTI\\zensynora\\myclaw\\tools\\toolbox.py", "source_location": "L254"}, {"caller_nid": "toolbox_register_tool", "callee": "getattr", "source_file": "F:\\ANTI\\zensynora\\myclaw\\tools\\toolbox.py", "source_location": "L255"}, {"caller_nid": "toolbox_register_tool", "callee": "unlink", "source_file": "F:\\ANTI\\zensynora\\myclaw\\tools\\toolbox.py", "source_location": "L257"}, {"caller_nid": "toolbox_register_tool", "callee": "unlink", "source_file": "F:\\ANTI\\zensynora\\myclaw\\tools\\toolbox.py", "source_location": "L260"}, {"caller_nid": "toolbox_register_tool", "callee": "clear", "source_file": "F:\\ANTI\\zensynora\\myclaw\\tools\\toolbox.py", "source_location": "L266"}, {"caller_nid": "toolbox_register_tool", "callee": "extend", "source_file": "F:\\ANTI\\zensynora\\myclaw\\tools\\toolbox.py", "source_location": "L267"}, {"caller_nid": "toolbox_register_tool", "callee": "_generate_schemas", "source_file": "F:\\ANTI\\zensynora\\myclaw\\tools\\toolbox.py", "source_location": "L267"}, {"caller_nid": "toolbox_register_tool", "callee": "exists", "source_file": "F:\\ANTI\\zensynora\\myclaw\\tools\\toolbox.py", "source_location": "L271"}, {"caller_nid": "toolbox_register_tool", "callee": "loads", "source_file": "F:\\ANTI\\zensynora\\myclaw\\tools\\toolbox.py", "source_location": "L273"}, {"caller_nid": "toolbox_register_tool", "callee": "read_text", "source_file": "F:\\ANTI\\zensynora\\myclaw\\tools\\toolbox.py", "source_location": "L273"}, {"caller_nid": "toolbox_register_tool", "callee": "str", "source_file": "F:\\ANTI\\zensynora\\myclaw\\tools\\toolbox.py", "source_location": "L278"}, {"caller_nid": "toolbox_register_tool", "callee": "isoformat", "source_file": "F:\\ANTI\\zensynora\\myclaw\\tools\\toolbox.py", "source_location": "L284"}, {"caller_nid": "toolbox_register_tool", "callee": "now", "source_file": "F:\\ANTI\\zensynora\\myclaw\\tools\\toolbox.py", "source_location": "L284"}, {"caller_nid": "toolbox_register_tool", "callee": "isoformat", "source_file": "F:\\ANTI\\zensynora\\myclaw\\tools\\toolbox.py", "source_location": "L285"}, {"caller_nid": "toolbox_register_tool", "callee": "now", "source_file": "F:\\ANTI\\zensynora\\myclaw\\tools\\toolbox.py", "source_location": "L285"}, {"caller_nid": "toolbox_register_tool", "callee": "write_text", "source_file": "F:\\ANTI\\zensynora\\myclaw\\tools\\toolbox.py", "source_location": "L291"}, {"caller_nid": "toolbox_register_tool", "callee": "dumps", "source_file": "F:\\ANTI\\zensynora\\myclaw\\tools\\toolbox.py", "source_location": "L291"}, {"caller_nid": "toolbox_register_tool", "callee": "info", "source_file": "F:\\ANTI\\zensynora\\myclaw\\tools\\toolbox.py", "source_location": "L293"}, {"caller_nid": "toolbox_update_toolbox_readme", "callee": "exists", "source_file": "F:\\ANTI\\zensynora\\myclaw\\tools\\toolbox.py", "source_location": "L306"}, {"caller_nid": "toolbox_update_toolbox_readme", "callee": "loads", "source_file": "F:\\ANTI\\zensynora\\myclaw\\tools\\toolbox.py", "source_location": "L308"}, {"caller_nid": "toolbox_update_toolbox_readme", "callee": "read_text", "source_file": "F:\\ANTI\\zensynora\\myclaw\\tools\\toolbox.py", "source_location": "L308"}, {"caller_nid": "toolbox_update_toolbox_readme", "callee": "sorted", "source_file": "F:\\ANTI\\zensynora\\myclaw\\tools\\toolbox.py", "source_location": "L309"}, {"caller_nid": "toolbox_update_toolbox_readme", "callee": "items", "source_file": "F:\\ANTI\\zensynora\\myclaw\\tools\\toolbox.py", "source_location": "L309"}, {"caller_nid": "toolbox_update_toolbox_readme", "callee": "get", "source_file": "F:\\ANTI\\zensynora\\myclaw\\tools\\toolbox.py", "source_location": "L311"}, {"caller_nid": "toolbox_update_toolbox_readme", "callee": "get", "source_file": "F:\\ANTI\\zensynora\\myclaw\\tools\\toolbox.py", "source_location": "L313"}, {"caller_nid": "toolbox_update_toolbox_readme", "callee": "write_text", "source_file": "F:\\ANTI\\zensynora\\myclaw\\tools\\toolbox.py", "source_location": "L334"}, {"caller_nid": "toolbox_list_toolbox", "callee": "exists", "source_file": "F:\\ANTI\\zensynora\\myclaw\\tools\\toolbox.py", "source_location": "L349"}, {"caller_nid": "toolbox_list_toolbox", "callee": "loads", "source_file": "F:\\ANTI\\zensynora\\myclaw\\tools\\toolbox.py", "source_location": "L353"}, {"caller_nid": "toolbox_list_toolbox", "callee": "read_text", "source_file": "F:\\ANTI\\zensynora\\myclaw\\tools\\toolbox.py", "source_location": "L353"}, {"caller_nid": "toolbox_list_toolbox", "callee": "sorted", "source_file": "F:\\ANTI\\zensynora\\myclaw\\tools\\toolbox.py", "source_location": "L358"}, {"caller_nid": "toolbox_list_toolbox", "callee": "items", "source_file": "F:\\ANTI\\zensynora\\myclaw\\tools\\toolbox.py", "source_location": "L358"}, {"caller_nid": "toolbox_list_toolbox", "callee": "get", "source_file": "F:\\ANTI\\zensynora\\myclaw\\tools\\toolbox.py", "source_location": "L359"}, {"caller_nid": "toolbox_list_toolbox", "callee": "get", "source_file": "F:\\ANTI\\zensynora\\myclaw\\tools\\toolbox.py", "source_location": "L361"}, {"caller_nid": "toolbox_list_toolbox", "callee": "append", "source_file": "F:\\ANTI\\zensynora\\myclaw\\tools\\toolbox.py", "source_location": "L363"}, {"caller_nid": "toolbox_list_toolbox", "callee": "get", "source_file": "F:\\ANTI\\zensynora\\myclaw\\tools\\toolbox.py", "source_location": "L363"}, {"caller_nid": "toolbox_list_toolbox", "callee": "append", "source_file": "F:\\ANTI\\zensynora\\myclaw\\tools\\toolbox.py", "source_location": "L364"}, {"caller_nid": "toolbox_list_toolbox", "callee": "get", "source_file": "F:\\ANTI\\zensynora\\myclaw\\tools\\toolbox.py", "source_location": "L364"}, {"caller_nid": "toolbox_list_toolbox", "callee": "append", "source_file": "F:\\ANTI\\zensynora\\myclaw\\tools\\toolbox.py", "source_location": "L365"}, {"caller_nid": "toolbox_list_toolbox", "callee": "get", "source_file": "F:\\ANTI\\zensynora\\myclaw\\tools\\toolbox.py", "source_location": "L365"}, {"caller_nid": "toolbox_list_toolbox", "callee": "get", "source_file": "F:\\ANTI\\zensynora\\myclaw\\tools\\toolbox.py", "source_location": "L366"}, {"caller_nid": "toolbox_list_toolbox", "callee": "append", "source_file": "F:\\ANTI\\zensynora\\myclaw\\tools\\toolbox.py", "source_location": "L367"}, {"caller_nid": "toolbox_list_toolbox", "callee": "join", "source_file": "F:\\ANTI\\zensynora\\myclaw\\tools\\toolbox.py", "source_location": "L367"}, {"caller_nid": "toolbox_list_toolbox", "callee": "get", "source_file": "F:\\ANTI\\zensynora\\myclaw\\tools\\toolbox.py", "source_location": "L367"}, {"caller_nid": "toolbox_list_toolbox", "callee": "append", "source_file": "F:\\ANTI\\zensynora\\myclaw\\tools\\toolbox.py", "source_location": "L368"}, {"caller_nid": "toolbox_list_toolbox", "callee": "get", "source_file": "F:\\ANTI\\zensynora\\myclaw\\tools\\toolbox.py", "source_location": "L368"}, {"caller_nid": "toolbox_list_toolbox", "callee": "append", "source_file": "F:\\ANTI\\zensynora\\myclaw\\tools\\toolbox.py", "source_location": "L370"}, {"caller_nid": "toolbox_list_toolbox", "callee": "get", "source_file": "F:\\ANTI\\zensynora\\myclaw\\tools\\toolbox.py", "source_location": "L370"}, {"caller_nid": "toolbox_list_toolbox", "callee": "append", "source_file": "F:\\ANTI\\zensynora\\myclaw\\tools\\toolbox.py", "source_location": "L371"}, {"caller_nid": "toolbox_list_toolbox", "callee": "join", "source_file": "F:\\ANTI\\zensynora\\myclaw\\tools\\toolbox.py", "source_location": "L373"}, {"caller_nid": "toolbox_list_toolbox", "callee": "error", "source_file": "F:\\ANTI\\zensynora\\myclaw\\tools\\toolbox.py", "source_location": "L375"}, {"caller_nid": "toolbox_get_tool_documentation", "callee": "exists", "source_file": "F:\\ANTI\\zensynora\\myclaw\\tools\\toolbox.py", "source_location": "L395"}, {"caller_nid": "toolbox_get_tool_documentation", "callee": "read_text", "source_file": "F:\\ANTI\\zensynora\\myclaw\\tools\\toolbox.py", "source_location": "L399"}, {"caller_nid": "toolbox_get_tool_documentation", "callee": "error", "source_file": "F:\\ANTI\\zensynora\\myclaw\\tools\\toolbox.py", "source_location": "L401"}, {"caller_nid": "toolbox_load_custom_tools", "callee": "exists", "source_file": "F:\\ANTI\\zensynora\\myclaw\\tools\\toolbox.py", "source_location": "L407"}, {"caller_nid": "toolbox_load_custom_tools", "callee": "loads", "source_file": "F:\\ANTI\\zensynora\\myclaw\\tools\\toolbox.py", "source_location": "L410"}, {"caller_nid": "toolbox_load_custom_tools", "callee": "read_text", "source_file": "F:\\ANTI\\zensynora\\myclaw\\tools\\toolbox.py", "source_location": "L410"}, {"caller_nid": "toolbox_load_custom_tools", "callee": "items", "source_file": "F:\\ANTI\\zensynora\\myclaw\\tools\\toolbox.py", "source_location": "L411"}, {"caller_nid": "toolbox_load_custom_tools", "callee": "isinstance", "source_file": "F:\\ANTI\\zensynora\\myclaw\\tools\\toolbox.py", "source_location": "L412"}, {"caller_nid": "toolbox_load_custom_tools", "callee": "Path", "source_file": "F:\\ANTI\\zensynora\\myclaw\\tools\\toolbox.py", "source_location": "L413"}, {"caller_nid": "toolbox_load_custom_tools", "callee": "get", "source_file": "F:\\ANTI\\zensynora\\myclaw\\tools\\toolbox.py", "source_location": "L413"}, {"caller_nid": "toolbox_load_custom_tools", "callee": "Path", "source_file": "F:\\ANTI\\zensynora\\myclaw\\tools\\toolbox.py", "source_location": "L416"}, {"caller_nid": "toolbox_load_custom_tools", "callee": "exists", "source_file": "F:\\ANTI\\zensynora\\myclaw\\tools\\toolbox.py", "source_location": "L418"}, {"caller_nid": "toolbox_load_custom_tools", "callee": "warning", "source_file": "F:\\ANTI\\zensynora\\myclaw\\tools\\toolbox.py", "source_location": "L419"}, {"caller_nid": "toolbox_load_custom_tools", "callee": "isinstance", "source_file": "F:\\ANTI\\zensynora\\myclaw\\tools\\toolbox.py", "source_location": "L423"}, {"caller_nid": "toolbox_load_custom_tools", "callee": "get", "source_file": "F:\\ANTI\\zensynora\\myclaw\\tools\\toolbox.py", "source_location": "L423"}, {"caller_nid": "toolbox_load_custom_tools", "callee": "info", "source_file": "F:\\ANTI\\zensynora\\myclaw\\tools\\toolbox.py", "source_location": "L424"}, {"caller_nid": "toolbox_load_custom_tools", "callee": "spec_from_file_location", "source_file": "F:\\ANTI\\zensynora\\myclaw\\tools\\toolbox.py", "source_location": "L428"}, {"caller_nid": "toolbox_load_custom_tools", "callee": "warning", "source_file": "F:\\ANTI\\zensynora\\myclaw\\tools\\toolbox.py", "source_location": "L430"}, {"caller_nid": "toolbox_load_custom_tools", "callee": "module_from_spec", "source_file": "F:\\ANTI\\zensynora\\myclaw\\tools\\toolbox.py", "source_location": "L432"}, {"caller_nid": "toolbox_load_custom_tools", "callee": "exec_module", "source_file": "F:\\ANTI\\zensynora\\myclaw\\tools\\toolbox.py", "source_location": "L433"}, {"caller_nid": "toolbox_load_custom_tools", "callee": "getattr", "source_file": "F:\\ANTI\\zensynora\\myclaw\\tools\\toolbox.py", "source_location": "L434"}, {"caller_nid": "toolbox_load_custom_tools", "callee": "info", "source_file": "F:\\ANTI\\zensynora\\myclaw\\tools\\toolbox.py", "source_location": "L436"}, {"caller_nid": "toolbox_load_custom_tools", "callee": "warning", "source_file": "F:\\ANTI\\zensynora\\myclaw\\tools\\toolbox.py", "source_location": "L438"}, {"caller_nid": "toolbox_load_custom_tools", "callee": "clear", "source_file": "F:\\ANTI\\zensynora\\myclaw\\tools\\toolbox.py", "source_location": "L444"}, {"caller_nid": "toolbox_load_custom_tools", "callee": "extend", "source_file": "F:\\ANTI\\zensynora\\myclaw\\tools\\toolbox.py", "source_location": "L445"}, {"caller_nid": "toolbox_load_custom_tools", "callee": "_generate_schemas", "source_file": "F:\\ANTI\\zensynora\\myclaw\\tools\\toolbox.py", "source_location": "L445"}, {"caller_nid": "toolbox_load_custom_tools", "callee": "error", "source_file": "F:\\ANTI\\zensynora\\myclaw\\tools\\toolbox.py", "source_location": "L447"}, {"caller_nid": "toolbox_get_skill_info", "callee": "exists", "source_file": "F:\\ANTI\\zensynora\\myclaw\\tools\\toolbox.py", "source_location": "L461"}, {"caller_nid": "toolbox_get_skill_info", "callee": "loads", "source_file": "F:\\ANTI\\zensynora\\myclaw\\tools\\toolbox.py", "source_location": "L465"}, {"caller_nid": "toolbox_get_skill_info", "callee": "read_text", "source_file": "F:\\ANTI\\zensynora\\myclaw\\tools\\toolbox.py", "source_location": "L465"}, {"caller_nid": "toolbox_get_skill_info", "callee": "get", "source_file": "F:\\ANTI\\zensynora\\myclaw\\tools\\toolbox.py", "source_location": "L474"}, {"caller_nid": "toolbox_get_skill_info", "callee": "get", "source_file": "F:\\ANTI\\zensynora\\myclaw\\tools\\toolbox.py", "source_location": "L475"}, {"caller_nid": "toolbox_get_skill_info", "callee": "get", "source_file": "F:\\ANTI\\zensynora\\myclaw\\tools\\toolbox.py", "source_location": "L476"}, {"caller_nid": "toolbox_get_skill_info", "callee": "get", "source_file": "F:\\ANTI\\zensynora\\myclaw\\tools\\toolbox.py", "source_location": "L477"}, {"caller_nid": "toolbox_get_skill_info", "callee": "get", "source_file": "F:\\ANTI\\zensynora\\myclaw\\tools\\toolbox.py", "source_location": "L478"}, {"caller_nid": "toolbox_get_skill_info", "callee": "get", "source_file": "F:\\ANTI\\zensynora\\myclaw\\tools\\toolbox.py", "source_location": "L481"}, {"caller_nid": "toolbox_get_skill_info", "callee": "append", "source_file": "F:\\ANTI\\zensynora\\myclaw\\tools\\toolbox.py", "source_location": "L482"}, {"caller_nid": "toolbox_get_skill_info", "callee": "join", "source_file": "F:\\ANTI\\zensynora\\myclaw\\tools\\toolbox.py", "source_location": "L482"}, {"caller_nid": "toolbox_get_skill_info", "callee": "get", "source_file": "F:\\ANTI\\zensynora\\myclaw\\tools\\toolbox.py", "source_location": "L482"}, {"caller_nid": "toolbox_get_skill_info", "callee": "get", "source_file": "F:\\ANTI\\zensynora\\myclaw\\tools\\toolbox.py", "source_location": "L484"}, {"caller_nid": "toolbox_get_skill_info", "callee": "append", "source_file": "F:\\ANTI\\zensynora\\myclaw\\tools\\toolbox.py", "source_location": "L485"}, {"caller_nid": "toolbox_get_skill_info", "callee": "get", "source_file": "F:\\ANTI\\zensynora\\myclaw\\tools\\toolbox.py", "source_location": "L485"}, {"caller_nid": "toolbox_get_skill_info", "callee": "extend", "source_file": "F:\\ANTI\\zensynora\\myclaw\\tools\\toolbox.py", "source_location": "L487"}, {"caller_nid": "toolbox_get_skill_info", "callee": "get", "source_file": "F:\\ANTI\\zensynora\\myclaw\\tools\\toolbox.py", "source_location": "L489"}, {"caller_nid": "toolbox_get_skill_info", "callee": "get", "source_file": "F:\\ANTI\\zensynora\\myclaw\\tools\\toolbox.py", "source_location": "L490"}, {"caller_nid": "toolbox_get_skill_info", "callee": "get", "source_file": "F:\\ANTI\\zensynora\\myclaw\\tools\\toolbox.py", "source_location": "L491"}, {"caller_nid": "toolbox_get_skill_info", "callee": "get", "source_file": "F:\\ANTI\\zensynora\\myclaw\\tools\\toolbox.py", "source_location": "L495"}, {"caller_nid": "toolbox_get_skill_info", "callee": "append", "source_file": "F:\\ANTI\\zensynora\\myclaw\\tools\\toolbox.py", "source_location": "L496"}, {"caller_nid": "toolbox_get_skill_info", "callee": "len", "source_file": "F:\\ANTI\\zensynora\\myclaw\\tools\\toolbox.py", "source_location": "L496"}, {"caller_nid": "toolbox_get_skill_info", "callee": "join", "source_file": "F:\\ANTI\\zensynora\\myclaw\\tools\\toolbox.py", "source_location": "L498"}, {"caller_nid": "toolbox_get_skill_info", "callee": "error", "source_file": "F:\\ANTI\\zensynora\\myclaw\\tools\\toolbox.py", "source_location": "L501"}, {"caller_nid": "toolbox_enable_skill", "callee": "exists", "source_file": "F:\\ANTI\\zensynora\\myclaw\\tools\\toolbox.py", "source_location": "L513"}, {"caller_nid": "toolbox_enable_skill", "callee": "loads", "source_file": "F:\\ANTI\\zensynora\\myclaw\\tools\\toolbox.py", "source_location": "L517"}, {"caller_nid": "toolbox_enable_skill", "callee": "read_text", "source_file": "F:\\ANTI\\zensynora\\myclaw\\tools\\toolbox.py", "source_location": "L517"}, {"caller_nid": "toolbox_enable_skill", "callee": "write_text", "source_file": "F:\\ANTI\\zensynora\\myclaw\\tools\\toolbox.py", "source_location": "L523"}, {"caller_nid": "toolbox_enable_skill", "callee": "dumps", "source_file": "F:\\ANTI\\zensynora\\myclaw\\tools\\toolbox.py", "source_location": "L523"}, {"caller_nid": "toolbox_enable_skill", "callee": "Path", "source_file": "F:\\ANTI\\zensynora\\myclaw\\tools\\toolbox.py", "source_location": "L528"}, {"caller_nid": "toolbox_enable_skill", "callee": "get", "source_file": "F:\\ANTI\\zensynora\\myclaw\\tools\\toolbox.py", "source_location": "L528"}, {"caller_nid": "toolbox_enable_skill", "callee": "exists", "source_file": "F:\\ANTI\\zensynora\\myclaw\\tools\\toolbox.py", "source_location": "L529"}, {"caller_nid": "toolbox_enable_skill", "callee": "spec_from_file_location", "source_file": "F:\\ANTI\\zensynora\\myclaw\\tools\\toolbox.py", "source_location": "L531"}, {"caller_nid": "toolbox_enable_skill", "callee": "module_from_spec", "source_file": "F:\\ANTI\\zensynora\\myclaw\\tools\\toolbox.py", "source_location": "L533"}, {"caller_nid": "toolbox_enable_skill", "callee": "exec_module", "source_file": "F:\\ANTI\\zensynora\\myclaw\\tools\\toolbox.py", "source_location": "L534"}, {"caller_nid": "toolbox_enable_skill", "callee": "getattr", "source_file": "F:\\ANTI\\zensynora\\myclaw\\tools\\toolbox.py", "source_location": "L535"}, {"caller_nid": "toolbox_enable_skill", "callee": "info", "source_file": "F:\\ANTI\\zensynora\\myclaw\\tools\\toolbox.py", "source_location": "L540"}, {"caller_nid": "toolbox_enable_skill", "callee": "clear", "source_file": "F:\\ANTI\\zensynora\\myclaw\\tools\\toolbox.py", "source_location": "L544"}, {"caller_nid": "toolbox_enable_skill", "callee": "extend", "source_file": "F:\\ANTI\\zensynora\\myclaw\\tools\\toolbox.py", "source_location": "L545"}, {"caller_nid": "toolbox_enable_skill", "callee": "_generate_schemas", "source_file": "F:\\ANTI\\zensynora\\myclaw\\tools\\toolbox.py", "source_location": "L545"}, {"caller_nid": "toolbox_enable_skill", "callee": "error", "source_file": "F:\\ANTI\\zensynora\\myclaw\\tools\\toolbox.py", "source_location": "L550"}, {"caller_nid": "toolbox_disable_skill", "callee": "exists", "source_file": "F:\\ANTI\\zensynora\\myclaw\\tools\\toolbox.py", "source_location": "L562"}, {"caller_nid": "toolbox_disable_skill", "callee": "loads", "source_file": "F:\\ANTI\\zensynora\\myclaw\\tools\\toolbox.py", "source_location": "L566"}, {"caller_nid": "toolbox_disable_skill", "callee": "read_text", "source_file": "F:\\ANTI\\zensynora\\myclaw\\tools\\toolbox.py", "source_location": "L566"}, {"caller_nid": "toolbox_disable_skill", "callee": "write_text", "source_file": "F:\\ANTI\\zensynora\\myclaw\\tools\\toolbox.py", "source_location": "L572"}, {"caller_nid": "toolbox_disable_skill", "callee": "dumps", "source_file": "F:\\ANTI\\zensynora\\myclaw\\tools\\toolbox.py", "source_location": "L572"}, {"caller_nid": "toolbox_disable_skill", "callee": "clear", "source_file": "F:\\ANTI\\zensynora\\myclaw\\tools\\toolbox.py", "source_location": "L577"}, {"caller_nid": "toolbox_disable_skill", "callee": "extend", "source_file": "F:\\ANTI\\zensynora\\myclaw\\tools\\toolbox.py", "source_location": "L578"}, {"caller_nid": "toolbox_disable_skill", "callee": "_generate_schemas", "source_file": "F:\\ANTI\\zensynora\\myclaw\\tools\\toolbox.py", "source_location": "L578"}, {"caller_nid": "toolbox_disable_skill", "callee": "info", "source_file": "F:\\ANTI\\zensynora\\myclaw\\tools\\toolbox.py", "source_location": "L580"}, {"caller_nid": "toolbox_disable_skill", "callee": "error", "source_file": "F:\\ANTI\\zensynora\\myclaw\\tools\\toolbox.py", "source_location": "L584"}, {"caller_nid": "toolbox_update_skill_metadata", "callee": "exists", "source_file": "F:\\ANTI\\zensynora\\myclaw\\tools\\toolbox.py", "source_location": "L601"}, {"caller_nid": "toolbox_update_skill_metadata", "callee": "loads", "source_file": "F:\\ANTI\\zensynora\\myclaw\\tools\\toolbox.py", "source_location": "L605"}, {"caller_nid": "toolbox_update_skill_metadata", "callee": "read_text", "source_file": "F:\\ANTI\\zensynora\\myclaw\\tools\\toolbox.py", "source_location": "L605"}, {"caller_nid": "toolbox_update_skill_metadata", "callee": "strip", "source_file": "F:\\ANTI\\zensynora\\myclaw\\tools\\toolbox.py", "source_location": "L611"}, {"caller_nid": "toolbox_update_skill_metadata", "callee": "split", "source_file": "F:\\ANTI\\zensynora\\myclaw\\tools\\toolbox.py", "source_location": "L611"}, {"caller_nid": "toolbox_update_skill_metadata", "callee": "strip", "source_file": "F:\\ANTI\\zensynora\\myclaw\\tools\\toolbox.py", "source_location": "L611"}, {"caller_nid": "toolbox_update_skill_metadata", "callee": "exists", "source_file": "F:\\ANTI\\zensynora\\myclaw\\tools\\toolbox.py", "source_location": "L617"}, {"caller_nid": "toolbox_update_skill_metadata", "callee": "read_text", "source_file": "F:\\ANTI\\zensynora\\myclaw\\tools\\toolbox.py", "source_location": "L618"}, {"caller_nid": "toolbox_update_skill_metadata", "callee": "split", "source_file": "F:\\ANTI\\zensynora\\myclaw\\tools\\toolbox.py", "source_location": "L621"}, {"caller_nid": "toolbox_update_skill_metadata", "callee": "split", "source_file": "F:\\ANTI\\zensynora\\myclaw\\tools\\toolbox.py", "source_location": "L623"}, {"caller_nid": "toolbox_update_skill_metadata", "callee": "split", "source_file": "F:\\ANTI\\zensynora\\myclaw\\tools\\toolbox.py", "source_location": "L623"}, {"caller_nid": "toolbox_update_skill_metadata", "callee": "write_text", "source_file": "F:\\ANTI\\zensynora\\myclaw\\tools\\toolbox.py", "source_location": "L625"}, {"caller_nid": "toolbox_update_skill_metadata", "callee": "isoformat", "source_file": "F:\\ANTI\\zensynora\\myclaw\\tools\\toolbox.py", "source_location": "L630"}, {"caller_nid": "toolbox_update_skill_metadata", "callee": "now", "source_file": "F:\\ANTI\\zensynora\\myclaw\\tools\\toolbox.py", "source_location": "L630"}, {"caller_nid": "toolbox_update_skill_metadata", "callee": "write_text", "source_file": "F:\\ANTI\\zensynora\\myclaw\\tools\\toolbox.py", "source_location": "L631"}, {"caller_nid": "toolbox_update_skill_metadata", "callee": "dumps", "source_file": "F:\\ANTI\\zensynora\\myclaw\\tools\\toolbox.py", "source_location": "L631"}, {"caller_nid": "toolbox_update_skill_metadata", "callee": "error", "source_file": "F:\\ANTI\\zensynora\\myclaw\\tools\\toolbox.py", "source_location": "L636"}, {"caller_nid": "toolbox_benchmark_skill", "callee": "exists", "source_file": "F:\\ANTI\\zensynora\\myclaw\\tools\\toolbox.py", "source_location": "L650"}, {"caller_nid": "toolbox_benchmark_skill", "callee": "loads", "source_file": "F:\\ANTI\\zensynora\\myclaw\\tools\\toolbox.py", "source_location": "L654"}, {"caller_nid": "toolbox_benchmark_skill", "callee": "read_text", "source_file": "F:\\ANTI\\zensynora\\myclaw\\tools\\toolbox.py", "source_location": "L654"}, {"caller_nid": "toolbox_benchmark_skill", "callee": "getattr", "source_file": "F:\\ANTI\\zensynora\\myclaw\\tools\\toolbox.py", "source_location": "L661"}, {"caller_nid": "toolbox_benchmark_skill", "callee": "getattr", "source_file": "F:\\ANTI\\zensynora\\myclaw\\tools\\toolbox.py", "source_location": "L662"}, {"caller_nid": "toolbox_benchmark_skill", "callee": "_is_untrusted_skill", "source_file": "F:\\ANTI\\zensynora\\myclaw\\tools\\toolbox.py", "source_location": "L663"}, {"caller_nid": "toolbox_benchmark_skill", "callee": "_validate_skill_for_sandbox", "source_file": "F:\\ANTI\\zensynora\\myclaw\\tools\\toolbox.py", "source_location": "L664"}, {"caller_nid": "toolbox_benchmark_skill", "callee": "loads", "source_file": "F:\\ANTI\\zensynora\\myclaw\\tools\\toolbox.py", "source_location": "L668"}, {"caller_nid": "toolbox_benchmark_skill", "callee": "enumerate", "source_file": "F:\\ANTI\\zensynora\\myclaw\\tools\\toolbox.py", "source_location": "L677"}, {"caller_nid": "toolbox_benchmark_skill", "callee": "get", "source_file": "F:\\ANTI\\zensynora\\myclaw\\tools\\toolbox.py", "source_location": "L679"}, {"caller_nid": "toolbox_benchmark_skill", "callee": "get", "source_file": "F:\\ANTI\\zensynora\\myclaw\\tools\\toolbox.py", "source_location": "L680"}, {"caller_nid": "toolbox_benchmark_skill", "callee": "iscoroutinefunction", "source_file": "F:\\ANTI\\zensynora\\myclaw\\tools\\toolbox.py", "source_location": "L683"}, {"caller_nid": "toolbox_benchmark_skill", "callee": "run_async", "source_file": "F:\\ANTI\\zensynora\\myclaw\\tools\\toolbox.py", "source_location": "L684"}, {"caller_nid": "toolbox_benchmark_skill", "callee": "func", "source_file": "F:\\ANTI\\zensynora\\myclaw\\tools\\toolbox.py", "source_location": "L686"}, {"caller_nid": "toolbox_benchmark_skill", "callee": "str", "source_file": "F:\\ANTI\\zensynora\\myclaw\\tools\\toolbox.py", "source_location": "L691"}, {"caller_nid": "toolbox_benchmark_skill", "callee": "str", "source_file": "F:\\ANTI\\zensynora\\myclaw\\tools\\toolbox.py", "source_location": "L691"}, {"caller_nid": "toolbox_benchmark_skill", "callee": "append", "source_file": "F:\\ANTI\\zensynora\\myclaw\\tools\\toolbox.py", "source_location": "L699"}, {"caller_nid": "toolbox_benchmark_skill", "callee": "append", "source_file": "F:\\ANTI\\zensynora\\myclaw\\tools\\toolbox.py", "source_location": "L701"}, {"caller_nid": "toolbox_benchmark_skill", "callee": "str", "source_file": "F:\\ANTI\\zensynora\\myclaw\\tools\\toolbox.py", "source_location": "L701"}, {"caller_nid": "toolbox_benchmark_skill", "callee": "append", "source_file": "F:\\ANTI\\zensynora\\myclaw\\tools\\toolbox.py", "source_location": "L704"}, {"caller_nid": "toolbox_benchmark_skill", "callee": "str", "source_file": "F:\\ANTI\\zensynora\\myclaw\\tools\\toolbox.py", "source_location": "L704"}, {"caller_nid": "toolbox_benchmark_skill", "callee": "len", "source_file": "F:\\ANTI\\zensynora\\myclaw\\tools\\toolbox.py", "source_location": "L706"}, {"caller_nid": "toolbox_benchmark_skill", "callee": "get", "source_file": "F:\\ANTI\\zensynora\\myclaw\\tools\\toolbox.py", "source_location": "L709"}, {"caller_nid": "toolbox_benchmark_skill", "callee": "get", "source_file": "F:\\ANTI\\zensynora\\myclaw\\tools\\toolbox.py", "source_location": "L710"}, {"caller_nid": "toolbox_benchmark_skill", "callee": "round", "source_file": "F:\\ANTI\\zensynora\\myclaw\\tools\\toolbox.py", "source_location": "L718"}, {"caller_nid": "toolbox_benchmark_skill", "callee": "len", "source_file": "F:\\ANTI\\zensynora\\myclaw\\tools\\toolbox.py", "source_location": "L722"}, {"caller_nid": "toolbox_benchmark_skill", "callee": "write_text", "source_file": "F:\\ANTI\\zensynora\\myclaw\\tools\\toolbox.py", "source_location": "L727"}, {"caller_nid": "toolbox_benchmark_skill", "callee": "dumps", "source_file": "F:\\ANTI\\zensynora\\myclaw\\tools\\toolbox.py", "source_location": "L727"}, {"caller_nid": "toolbox_benchmark_skill", "callee": "len", "source_file": "F:\\ANTI\\zensynora\\myclaw\\tools\\toolbox.py", "source_location": "L732"}, {"caller_nid": "toolbox_benchmark_skill", "callee": "len", "source_file": "F:\\ANTI\\zensynora\\myclaw\\tools\\toolbox.py", "source_location": "L734"}, {"caller_nid": "toolbox_benchmark_skill", "callee": "len", "source_file": "F:\\ANTI\\zensynora\\myclaw\\tools\\toolbox.py", "source_location": "L741"}, {"caller_nid": "toolbox_benchmark_skill", "callee": "append", "source_file": "F:\\ANTI\\zensynora\\myclaw\\tools\\toolbox.py", "source_location": "L742"}, {"caller_nid": "toolbox_benchmark_skill", "callee": "append", "source_file": "F:\\ANTI\\zensynora\\myclaw\\tools\\toolbox.py", "source_location": "L743"}, {"caller_nid": "toolbox_benchmark_skill", "callee": "join", "source_file": "F:\\ANTI\\zensynora\\myclaw\\tools\\toolbox.py", "source_location": "L745"}, {"caller_nid": "toolbox_benchmark_skill", "callee": "error", "source_file": "F:\\ANTI\\zensynora\\myclaw\\tools\\toolbox.py", "source_location": "L750"}, {"caller_nid": "toolbox_evaluate_skill", "callee": "exists", "source_file": "F:\\ANTI\\zensynora\\myclaw\\tools\\toolbox.py", "source_location": "L767"}, {"caller_nid": "toolbox_evaluate_skill", "callee": "loads", "source_file": "F:\\ANTI\\zensynora\\myclaw\\tools\\toolbox.py", "source_location": "L771"}, {"caller_nid": "toolbox_evaluate_skill", "callee": "read_text", "source_file": "F:\\ANTI\\zensynora\\myclaw\\tools\\toolbox.py", "source_location": "L771"}, {"caller_nid": "toolbox_evaluate_skill", "callee": "Path", "source_file": "F:\\ANTI\\zensynora\\myclaw\\tools\\toolbox.py", "source_location": "L777"}, {"caller_nid": "toolbox_evaluate_skill", "callee": "get", "source_file": "F:\\ANTI\\zensynora\\myclaw\\tools\\toolbox.py", "source_location": "L777"}, {"caller_nid": "toolbox_evaluate_skill", "callee": "exists", "source_file": "F:\\ANTI\\zensynora\\myclaw\\tools\\toolbox.py", "source_location": "L779"}, {"caller_nid": "toolbox_evaluate_skill", "callee": "append", "source_file": "F:\\ANTI\\zensynora\\myclaw\\tools\\toolbox.py", "source_location": "L788"}, {"caller_nid": "toolbox_evaluate_skill", "callee": "read_text", "source_file": "F:\\ANTI\\zensynora\\myclaw\\tools\\toolbox.py", "source_location": "L793"}, {"caller_nid": "toolbox_evaluate_skill", "callee": "compile", "source_file": "F:\\ANTI\\zensynora\\myclaw\\tools\\toolbox.py", "source_location": "L794"}, {"caller_nid": "toolbox_evaluate_skill", "callee": "append", "source_file": "F:\\ANTI\\zensynora\\myclaw\\tools\\toolbox.py", "source_location": "L795"}, {"caller_nid": "toolbox_evaluate_skill", "callee": "append", "source_file": "F:\\ANTI\\zensynora\\myclaw\\tools\\toolbox.py", "source_location": "L798"}, {"caller_nid": "toolbox_evaluate_skill", "callee": "append", "source_file": "F:\\ANTI\\zensynora\\myclaw\\tools\\toolbox.py", "source_location": "L799"}, {"caller_nid": "toolbox_evaluate_skill", "callee": "append", "source_file": "F:\\ANTI\\zensynora\\myclaw\\tools\\toolbox.py", "source_location": "L803"}, {"caller_nid": "toolbox_evaluate_skill", "callee": "append", "source_file": "F:\\ANTI\\zensynora\\myclaw\\tools\\toolbox.py", "source_location": "L806"}, {"caller_nid": "toolbox_evaluate_skill", "callee": "append", "source_file": "F:\\ANTI\\zensynora\\myclaw\\tools\\toolbox.py", "source_location": "L810"}, {"caller_nid": "toolbox_evaluate_skill", "callee": "append", "source_file": "F:\\ANTI\\zensynora\\myclaw\\tools\\toolbox.py", "source_location": "L813"}, {"caller_nid": "toolbox_evaluate_skill", "callee": "append", "source_file": "F:\\ANTI\\zensynora\\myclaw\\tools\\toolbox.py", "source_location": "L817"}, {"caller_nid": "toolbox_evaluate_skill", "callee": "append", "source_file": "F:\\ANTI\\zensynora\\myclaw\\tools\\toolbox.py", "source_location": "L820"}, {"caller_nid": "toolbox_evaluate_skill", "callee": "append", "source_file": "F:\\ANTI\\zensynora\\myclaw\\tools\\toolbox.py", "source_location": "L826"}, {"caller_nid": "toolbox_evaluate_skill", "callee": "append", "source_file": "F:\\ANTI\\zensynora\\myclaw\\tools\\toolbox.py", "source_location": "L829"}, {"caller_nid": "toolbox_evaluate_skill", "callee": "append", "source_file": "F:\\ANTI\\zensynora\\myclaw\\tools\\toolbox.py", "source_location": "L830"}, {"caller_nid": "toolbox_evaluate_skill", "callee": "join", "source_file": "F:\\ANTI\\zensynora\\myclaw\\tools\\toolbox.py", "source_location": "L830"}, {"caller_nid": "toolbox_evaluate_skill", "callee": "get", "source_file": "F:\\ANTI\\zensynora\\myclaw\\tools\\toolbox.py", "source_location": "L833"}, {"caller_nid": "toolbox_evaluate_skill", "callee": "get", "source_file": "F:\\ANTI\\zensynora\\myclaw\\tools\\toolbox.py", "source_location": "L834"}, {"caller_nid": "toolbox_evaluate_skill", "callee": "round", "source_file": "F:\\ANTI\\zensynora\\myclaw\\tools\\toolbox.py", "source_location": "L841"}, {"caller_nid": "toolbox_evaluate_skill", "callee": "write_text", "source_file": "F:\\ANTI\\zensynora\\myclaw\\tools\\toolbox.py", "source_location": "L843"}, {"caller_nid": "toolbox_evaluate_skill", "callee": "dumps", "source_file": "F:\\ANTI\\zensynora\\myclaw\\tools\\toolbox.py", "source_location": "L843"}, {"caller_nid": "toolbox_evaluate_skill", "callee": "append", "source_file": "F:\\ANTI\\zensynora\\myclaw\\tools\\toolbox.py", "source_location": "L856"}, {"caller_nid": "toolbox_evaluate_skill", "callee": "append", "source_file": "F:\\ANTI\\zensynora\\myclaw\\tools\\toolbox.py", "source_location": "L859"}, {"caller_nid": "toolbox_evaluate_skill", "callee": "append", "source_file": "F:\\ANTI\\zensynora\\myclaw\\tools\\toolbox.py", "source_location": "L860"}, {"caller_nid": "toolbox_evaluate_skill", "callee": "join", "source_file": "F:\\ANTI\\zensynora\\myclaw\\tools\\toolbox.py", "source_location": "L862"}, {"caller_nid": "toolbox_evaluate_skill", "callee": "error", "source_file": "F:\\ANTI\\zensynora\\myclaw\\tools\\toolbox.py", "source_location": "L865"}, {"caller_nid": "toolbox_improve_skill", "callee": "exists", "source_file": "F:\\ANTI\\zensynora\\myclaw\\tools\\toolbox.py", "source_location": "L886"}, {"caller_nid": "toolbox_improve_skill", "callee": "loads", "source_file": "F:\\ANTI\\zensynora\\myclaw\\tools\\toolbox.py", "source_location": "L890"}, {"caller_nid": "toolbox_improve_skill", "callee": "read_text", "source_file": "F:\\ANTI\\zensynora\\myclaw\\tools\\toolbox.py", "source_location": "L890"}, {"caller_nid": "toolbox_improve_skill", "callee": "isidentifier", "source_file": "F:\\ANTI\\zensynora\\myclaw\\tools\\toolbox.py", "source_location": "L899"}, {"caller_nid": "toolbox_improve_skill", "callee": "compile", "source_file": "F:\\ANTI\\zensynora\\myclaw\\tools\\toolbox.py", "source_location": "L904"}, {"caller_nid": "toolbox_improve_skill", "callee": "parse", "source_file": "F:\\ANTI\\zensynora\\myclaw\\tools\\toolbox.py", "source_location": "L912"}, {"caller_nid": "toolbox_improve_skill", "callee": "walk", "source_file": "F:\\ANTI\\zensynora\\myclaw\\tools\\toolbox.py", "source_location": "L926"}, {"caller_nid": "toolbox_improve_skill", "callee": "isinstance", "source_file": "F:\\ANTI\\zensynora\\myclaw\\tools\\toolbox.py", "source_location": "L927"}, {"caller_nid": "toolbox_improve_skill", "callee": "split", "source_file": "F:\\ANTI\\zensynora\\myclaw\\tools\\toolbox.py", "source_location": "L929"}, {"caller_nid": "toolbox_improve_skill", "callee": "isinstance", "source_file": "F:\\ANTI\\zensynora\\myclaw\\tools\\toolbox.py", "source_location": "L931"}, {"caller_nid": "toolbox_improve_skill", "callee": "split", "source_file": "F:\\ANTI\\zensynora\\myclaw\\tools\\toolbox.py", "source_location": "L932"}, {"caller_nid": "toolbox_improve_skill", "callee": "isinstance", "source_file": "F:\\ANTI\\zensynora\\myclaw\\tools\\toolbox.py", "source_location": "L934"}, {"caller_nid": "toolbox_improve_skill", "callee": "isinstance", "source_file": "F:\\ANTI\\zensynora\\myclaw\\tools\\toolbox.py", "source_location": "L935"}, {"caller_nid": "toolbox_improve_skill", "callee": "getattr", "source_file": "F:\\ANTI\\zensynora\\myclaw\\tools\\toolbox.py", "source_location": "L949"}, {"caller_nid": "toolbox_improve_skill", "callee": "getattr", "source_file": "F:\\ANTI\\zensynora\\myclaw\\tools\\toolbox.py", "source_location": "L949"}, {"caller_nid": "toolbox_improve_skill", "callee": "validate_code", "source_file": "F:\\ANTI\\zensynora\\myclaw\\tools\\toolbox.py", "source_location": "L950"}, {"caller_nid": "toolbox_improve_skill", "callee": "_get_security_sandbox", "source_file": "F:\\ANTI\\zensynora\\myclaw\\tools\\toolbox.py", "source_location": "L950"}, {"caller_nid": "toolbox_improve_skill", "callee": "join", "source_file": "F:\\ANTI\\zensynora\\myclaw\\tools\\toolbox.py", "source_location": "L952"}, {"caller_nid": "toolbox_improve_skill", "callee": "Path", "source_file": "F:\\ANTI\\zensynora\\myclaw\\tools\\toolbox.py", "source_location": "L955"}, {"caller_nid": "toolbox_improve_skill", "callee": "get", "source_file": "F:\\ANTI\\zensynora\\myclaw\\tools\\toolbox.py", "source_location": "L955"}, {"caller_nid": "toolbox_improve_skill", "callee": "exists", "source_file": "F:\\ANTI\\zensynora\\myclaw\\tools\\toolbox.py", "source_location": "L957"}, {"caller_nid": "toolbox_improve_skill", "callee": "with_suffix", "source_file": "F:\\ANTI\\zensynora\\myclaw\\tools\\toolbox.py", "source_location": "L958"}, {"caller_nid": "toolbox_improve_skill", "callee": "copy2", "source_file": "F:\\ANTI\\zensynora\\myclaw\\tools\\toolbox.py", "source_location": "L961"}, {"caller_nid": "toolbox_improve_skill", "callee": "write_text", "source_file": "F:\\ANTI\\zensynora\\myclaw\\tools\\toolbox.py", "source_location": "L964"}, {"caller_nid": "toolbox_improve_skill", "callee": "get", "source_file": "F:\\ANTI\\zensynora\\myclaw\\tools\\toolbox.py", "source_location": "L968"}, {"caller_nid": "toolbox_improve_skill", "callee": "isoformat", "source_file": "F:\\ANTI\\zensynora\\myclaw\\tools\\toolbox.py", "source_location": "L983"}, {"caller_nid": "toolbox_improve_skill", "callee": "now", "source_file": "F:\\ANTI\\zensynora\\myclaw\\tools\\toolbox.py", "source_location": "L983"}, {"caller_nid": "toolbox_improve_skill", "callee": "get", "source_file": "F:\\ANTI\\zensynora\\myclaw\\tools\\toolbox.py", "source_location": "L986"}, {"caller_nid": "toolbox_improve_skill", "callee": "write_text", "source_file": "F:\\ANTI\\zensynora\\myclaw\\tools\\toolbox.py", "source_location": "L991"}, {"caller_nid": "toolbox_improve_skill", "callee": "spec_from_file_location", "source_file": "F:\\ANTI\\zensynora\\myclaw\\tools\\toolbox.py", "source_location": "L995"}, {"caller_nid": "toolbox_improve_skill", "callee": "exists", "source_file": "F:\\ANTI\\zensynora\\myclaw\\tools\\toolbox.py", "source_location": "L998"}, {"caller_nid": "toolbox_improve_skill", "callee": "copy2", "source_file": "F:\\ANTI\\zensynora\\myclaw\\tools\\toolbox.py", "source_location": "L999"}, {"caller_nid": "toolbox_improve_skill", "callee": "module_from_spec", "source_file": "F:\\ANTI\\zensynora\\myclaw\\tools\\toolbox.py", "source_location": "L1002"}, {"caller_nid": "toolbox_improve_skill", "callee": "exec_module", "source_file": "F:\\ANTI\\zensynora\\myclaw\\tools\\toolbox.py", "source_location": "L1003"}, {"caller_nid": "toolbox_improve_skill", "callee": "getattr", "source_file": "F:\\ANTI\\zensynora\\myclaw\\tools\\toolbox.py", "source_location": "L1004"}, {"caller_nid": "toolbox_improve_skill", "callee": "exists", "source_file": "F:\\ANTI\\zensynora\\myclaw\\tools\\toolbox.py", "source_location": "L1011"}, {"caller_nid": "toolbox_improve_skill", "callee": "copy2", "source_file": "F:\\ANTI\\zensynora\\myclaw\\tools\\toolbox.py", "source_location": "L1012"}, {"caller_nid": "toolbox_improve_skill", "callee": "get", "source_file": "F:\\ANTI\\zensynora\\myclaw\\tools\\toolbox.py", "source_location": "L1016"}, {"caller_nid": "toolbox_improve_skill", "callee": "split", "source_file": "F:\\ANTI\\zensynora\\myclaw\\tools\\toolbox.py", "source_location": "L1018"}, {"caller_nid": "toolbox_improve_skill", "callee": "int", "source_file": "F:\\ANTI\\zensynora\\myclaw\\tools\\toolbox.py", "source_location": "L1019"}, {"caller_nid": "toolbox_improve_skill", "callee": "join", "source_file": "F:\\ANTI\\zensynora\\myclaw\\tools\\toolbox.py", "source_location": "L1020"}, {"caller_nid": "toolbox_improve_skill", "callee": "str", "source_file": "F:\\ANTI\\zensynora\\myclaw\\tools\\toolbox.py", "source_location": "L1020"}, {"caller_nid": "toolbox_improve_skill", "callee": "str", "source_file": "F:\\ANTI\\zensynora\\myclaw\\tools\\toolbox.py", "source_location": "L1026"}, {"caller_nid": "toolbox_improve_skill", "callee": "get", "source_file": "F:\\ANTI\\zensynora\\myclaw\\tools\\toolbox.py", "source_location": "L1029"}, {"caller_nid": "toolbox_improve_skill", "callee": "get", "source_file": "F:\\ANTI\\zensynora\\myclaw\\tools\\toolbox.py", "source_location": "L1030"}, {"caller_nid": "toolbox_improve_skill", "callee": "get", "source_file": "F:\\ANTI\\zensynora\\myclaw\\tools\\toolbox.py", "source_location": "L1032"}, {"caller_nid": "toolbox_improve_skill", "callee": "isoformat", "source_file": "F:\\ANTI\\zensynora\\myclaw\\tools\\toolbox.py", "source_location": "L1032"}, {"caller_nid": "toolbox_improve_skill", "callee": "now", "source_file": "F:\\ANTI\\zensynora\\myclaw\\tools\\toolbox.py", "source_location": "L1032"}, {"caller_nid": "toolbox_improve_skill", "callee": "isoformat", "source_file": "F:\\ANTI\\zensynora\\myclaw\\tools\\toolbox.py", "source_location": "L1033"}, {"caller_nid": "toolbox_improve_skill", "callee": "now", "source_file": "F:\\ANTI\\zensynora\\myclaw\\tools\\toolbox.py", "source_location": "L1033"}, {"caller_nid": "toolbox_improve_skill", "callee": "get", "source_file": "F:\\ANTI\\zensynora\\myclaw\\tools\\toolbox.py", "source_location": "L1034"}, {"caller_nid": "toolbox_improve_skill", "callee": "get", "source_file": "F:\\ANTI\\zensynora\\myclaw\\tools\\toolbox.py", "source_location": "L1035"}, {"caller_nid": "toolbox_improve_skill", "callee": "write_text", "source_file": "F:\\ANTI\\zensynora\\myclaw\\tools\\toolbox.py", "source_location": "L1039"}, {"caller_nid": "toolbox_improve_skill", "callee": "dumps", "source_file": "F:\\ANTI\\zensynora\\myclaw\\tools\\toolbox.py", "source_location": "L1039"}, {"caller_nid": "toolbox_improve_skill", "callee": "clear", "source_file": "F:\\ANTI\\zensynora\\myclaw\\tools\\toolbox.py", "source_location": "L1042"}, {"caller_nid": "toolbox_improve_skill", "callee": "extend", "source_file": "F:\\ANTI\\zensynora\\myclaw\\tools\\toolbox.py", "source_location": "L1043"}, {"caller_nid": "toolbox_improve_skill", "callee": "_generate_schemas", "source_file": "F:\\ANTI\\zensynora\\myclaw\\tools\\toolbox.py", "source_location": "L1043"}, {"caller_nid": "toolbox_improve_skill", "callee": "exists", "source_file": "F:\\ANTI\\zensynora\\myclaw\\tools\\toolbox.py", "source_location": "L1046"}, {"caller_nid": "toolbox_improve_skill", "callee": "unlink", "source_file": "F:\\ANTI\\zensynora\\myclaw\\tools\\toolbox.py", "source_location": "L1047"}, {"caller_nid": "toolbox_improve_skill", "callee": "info", "source_file": "F:\\ANTI\\zensynora\\myclaw\\tools\\toolbox.py", "source_location": "L1049"}, {"caller_nid": "toolbox_improve_skill", "callee": "error", "source_file": "F:\\ANTI\\zensynora\\myclaw\\tools\\toolbox.py", "source_location": "L1060"}, {"caller_nid": "toolbox_rollback_skill", "callee": "exists", "source_file": "F:\\ANTI\\zensynora\\myclaw\\tools\\toolbox.py", "source_location": "L1072"}, {"caller_nid": "toolbox_rollback_skill", "callee": "loads", "source_file": "F:\\ANTI\\zensynora\\myclaw\\tools\\toolbox.py", "source_location": "L1076"}, {"caller_nid": "toolbox_rollback_skill", "callee": "read_text", "source_file": "F:\\ANTI\\zensynora\\myclaw\\tools\\toolbox.py", "source_location": "L1076"}, {"caller_nid": "toolbox_rollback_skill", "callee": "Path", "source_file": "F:\\ANTI\\zensynora\\myclaw\\tools\\toolbox.py", "source_location": "L1082"}, {"caller_nid": "toolbox_rollback_skill", "callee": "get", "source_file": "F:\\ANTI\\zensynora\\myclaw\\tools\\toolbox.py", "source_location": "L1082"}, {"caller_nid": "toolbox_rollback_skill", "callee": "with_suffix", "source_file": "F:\\ANTI\\zensynora\\myclaw\\tools\\toolbox.py", "source_location": "L1083"}, {"caller_nid": "toolbox_rollback_skill", "callee": "exists", "source_file": "F:\\ANTI\\zensynora\\myclaw\\tools\\toolbox.py", "source_location": "L1085"}, {"caller_nid": "toolbox_rollback_skill", "callee": "copy2", "source_file": "F:\\ANTI\\zensynora\\myclaw\\tools\\toolbox.py", "source_location": "L1091"}, {"caller_nid": "toolbox_rollback_skill", "callee": "get", "source_file": "F:\\ANTI\\zensynora\\myclaw\\tools\\toolbox.py", "source_location": "L1094"}, {"caller_nid": "toolbox_rollback_skill", "callee": "split", "source_file": "F:\\ANTI\\zensynora\\myclaw\\tools\\toolbox.py", "source_location": "L1096"}, {"caller_nid": "toolbox_rollback_skill", "callee": "max", "source_file": "F:\\ANTI\\zensynora\\myclaw\\tools\\toolbox.py", "source_location": "L1097"}, {"caller_nid": "toolbox_rollback_skill", "callee": "int", "source_file": "F:\\ANTI\\zensynora\\myclaw\\tools\\toolbox.py", "source_location": "L1097"}, {"caller_nid": "toolbox_rollback_skill", "callee": "join", "source_file": "F:\\ANTI\\zensynora\\myclaw\\tools\\toolbox.py", "source_location": "L1098"}, {"caller_nid": "toolbox_rollback_skill", "callee": "str", "source_file": "F:\\ANTI\\zensynora\\myclaw\\tools\\toolbox.py", "source_location": "L1098"}, {"caller_nid": "toolbox_rollback_skill", "callee": "spec_from_file_location", "source_file": "F:\\ANTI\\zensynora\\myclaw\\tools\\toolbox.py", "source_location": "L1104"}, {"caller_nid": "toolbox_rollback_skill", "callee": "module_from_spec", "source_file": "F:\\ANTI\\zensynora\\myclaw\\tools\\toolbox.py", "source_location": "L1106"}, {"caller_nid": "toolbox_rollback_skill", "callee": "exec_module", "source_file": "F:\\ANTI\\zensynora\\myclaw\\tools\\toolbox.py", "source_location": "L1107"}, {"caller_nid": "toolbox_rollback_skill", "callee": "getattr", "source_file": "F:\\ANTI\\zensynora\\myclaw\\tools\\toolbox.py", "source_location": "L1108"}, {"caller_nid": "toolbox_rollback_skill", "callee": "isoformat", "source_file": "F:\\ANTI\\zensynora\\myclaw\\tools\\toolbox.py", "source_location": "L1118"}, {"caller_nid": "toolbox_rollback_skill", "callee": "now", "source_file": "F:\\ANTI\\zensynora\\myclaw\\tools\\toolbox.py", "source_location": "L1118"}, {"caller_nid": "toolbox_rollback_skill", "callee": "write_text", "source_file": "F:\\ANTI\\zensynora\\myclaw\\tools\\toolbox.py", "source_location": "L1119"}, {"caller_nid": "toolbox_rollback_skill", "callee": "dumps", "source_file": "F:\\ANTI\\zensynora\\myclaw\\tools\\toolbox.py", "source_location": "L1119"}, {"caller_nid": "toolbox_rollback_skill", "callee": "clear", "source_file": "F:\\ANTI\\zensynora\\myclaw\\tools\\toolbox.py", "source_location": "L1121"}, {"caller_nid": "toolbox_rollback_skill", "callee": "extend", "source_file": "F:\\ANTI\\zensynora\\myclaw\\tools\\toolbox.py", "source_location": "L1122"}, {"caller_nid": "toolbox_rollback_skill", "callee": "_generate_schemas", "source_file": "F:\\ANTI\\zensynora\\myclaw\\tools\\toolbox.py", "source_location": "L1122"}, {"caller_nid": "toolbox_rollback_skill", "callee": "error", "source_file": "F:\\ANTI\\zensynora\\myclaw\\tools\\toolbox.py", "source_location": "L1131"}]}