{"nodes": [{"id": "f_anti_zensynora_scrapling_scrapling_core_utils_init_py", "label": "__init__.py", "file_type": "code", "source_file": "F:\\ANTI\\zensynora\\Scrapling\\scrapling\\core\\utils\\__init__.py", "source_location": "L1"}], "edges": [{"source": "f_anti_zensynora_scrapling_scrapling_core_utils_init_py", "target": "f_anti_zensynora_scrapling_scrapling_core_utils_utils_py", "relation": "imports_from", "confidence": "EXTRACTED", "source_file": "F:\\ANTI\\zensynora\\Scrapling\\scrapling\\core\\utils\\__init__.py", "source_location": "L1", "weight": 1.0}], "raw_calls": []}